lep_downloader/__init__.py
lep_downloader/__main__.py
lep_downloader/cli.py
lep_downloader/cli_shared.py
lep_downloader/commands/__init__.py
lep_downloader/commands/download.py
lep_downloader/commands/parse.py
lep_downloader/config.py
lep_downloader/downloader.py
lep_downloader/exceptions.py
lep_downloader/lep.py
lep_downloader/parser.py
lep_downloader/py.typed
lep_downloader-3.0.0b3.dist-info/entry_points.txt
lep_downloader-3.0.0b3.dist-info/LICENSE.rst
lep_downloader-3.0.0b3.dist-info/WHEEL
lep_downloader-3.0.0b3.dist-info/METADATA
lep_downloader-3.0.0b3.dist-info/RECORD
