Metadata-Version: 2.1
Name: lep-downloader
Version: 3.0.0b3
Summary: LEP Downloader - CLI app for parsing and downloading episodes of Luke's English Podcast
Home-page: https://github.com/hotenov/LEP-downloader
License: MIT
Author: Artem Hotenov
Author-email: qa@hotenov.com
Requires-Python: >=3.8.0,<4.0.0
Classifier: Development Status :: 4 - Beta
Classifier: License :: OSI Approved :: MIT License
Classifier: Programming Language :: Python :: 3
Classifier: Programming Language :: Python :: 3.8
Classifier: Programming Language :: Python :: 3.9
Classifier: Programming Language :: Python :: 3.10
Classifier: Programming Language :: Python :: 3.10
Classifier: Programming Language :: Python :: 3.8
Classifier: Programming Language :: Python :: 3.9
Requires-Dist: beautifulsoup4 (>=4.9.3,<5.0.0)
Requires-Dist: click (>=8.0.4,<9.0.0)
Requires-Dist: loguru (>=0.6.0,<0.7.0)
Requires-Dist: lxml (>=4.9.1,<5.0.0)
Requires-Dist: requests (>=2.26.0,<3.0.0)
Requires-Dist: single-source (>=0.2.0,<0.3.0)
Project-URL: Changelog, https://github.com/hotenov/LEP-downloader/releases
Project-URL: Documentation, https://lep-downloader.readthedocs.io
Project-URL: Repository, https://github.com/hotenov/LEP-downloader
